py4xml/__init__.py
py4xml/py4xml.py
py4xml-1.2.1.dist-info/LICENSE
py4xml-1.2.1.dist-info/METADATA
py4xml-1.2.1.dist-info/WHEEL
py4xml-1.2.1.dist-info/top_level.txt
py4xml-1.2.1.dist-info/RECORD
