Metadata-Version: 2.1
Name: py4xml
Version: 1.2.1
Summary: A python package to read, write or interpret the XML files.
Home-page: https://github.com/MasterANK/py4xml
Author: Ankit Aggarwal
Author-email: ankitaggarwal200515@gmail.com
Project-URL: Bug Tracker, https://github.com/MasterANK/py4xml/issues
Classifier: Development Status :: 5 - Production/Stable
Classifier: Programming Language :: Python :: 3
Classifier: License :: OSI Approved :: MIT License
Classifier: Operating System :: OS Independent
Classifier: Topic :: Text Processing :: Markup :: XML
Requires-Python: >=3.6
License-File: LICENSE
